libmonty_tools/__init__.py
libmonty_tools/__main__.py
libmonty_tools/version.py
libmonty_tools/data/agr-wordlist-en-alt-edited-by-alan-beale.txt
libmonty_tools/data/agr-wordlist-en-original.txt
libmonty_tools/data/eff-large-wordlist.txt
libmonty_tools/data/eff-short-wordlist-1.txt
libmonty_tools/data/eff-short-wordlist-2-0.txt
libmonty_tools/easypass/__init__.py
libmonty_tools/easypass/dice_methods.py
libmonty_tools/easypass/easypass.py
libmonty_tools/soundboard/__init__.py
libmonty_tools/soundboard/config.py
libmonty_tools/soundboard/sound.py
libmonty_tools/soundboard/soundboard.py
libmonty_tools-0.1.0.dist-info/LICENSE
libmonty_tools-0.1.0.dist-info/METADATA
libmonty_tools-0.1.0.dist-info/WHEEL
libmonty_tools-0.1.0.dist-info/entry_points.txt
libmonty_tools-0.1.0.dist-info/top_level.txt
libmonty_tools-0.1.0.dist-info/RECORD
