Metadata-Version: 2.1
Name: libmonty-tools
Version: 0.1.0
Summary: libmonty-tools - Collection of Python tools and small apps
Home-page: https://codeberg.org/sunarch/libmonty-tools
Author: András Németh (sunarch)
Author-email: sunarch@protonmail.com
Maintainer: András Németh (sunarch)
Maintainer-email: sunarch@protonmail.com
License: Mozilla Public License 2.0 (MPL 2.0)
Project-URL: Bug Tracker, https://codeberg.org/sunarch/libmonty-tools/issues
Keywords: libmonty,tools
Platform: Any
Classifier: Development Status :: 3 - Alpha
Classifier: Intended Audience :: Developers
Classifier: Intended Audience :: End Users/Desktop
Classifier: License :: OSI Approved :: Mozilla Public License 2.0 (MPL 2.0)
Classifier: Natural Language :: English
Classifier: Operating System :: OS Independent
Classifier: Programming Language :: Python :: 3
Classifier: Topic :: Multimedia :: Sound/Audio
Classifier: Topic :: Office/Business
Classifier: Topic :: Security
Classifier: Typing :: Typed
Requires-Python: >=3.10
License-File: LICENSE
Requires-Dist: codetiming (==1.4.0)
Requires-Dist: libmonty-logging (==0.1.1)
Requires-Dist: pygame (==2.4.0)
Requires-Dist: xdg-base-dirs (==6.0.0)
